proper_pixel_art/__init__.py
proper_pixel_art/cli.py
proper_pixel_art/colors.py
proper_pixel_art/mesh.py
proper_pixel_art/pixelate.py
proper_pixel_art/utils.py
proper_pixel_art/web.py
proper_pixel_art-1.4.0.dist-info/METADATA
proper_pixel_art-1.4.0.dist-info/WHEEL
proper_pixel_art-1.4.0.dist-info/entry_points.txt
proper_pixel_art-1.4.0.dist-info/licenses/LICENSE
proper_pixel_art-1.4.0.dist-info/RECORD
