Metadata-Version: 2.4
Name: proper-pixel-art
Version: 1.4.0
Summary: Converts pixel-art-style images such as those from generative models or low-quality sprite web uploads to true resolution usable assets.
Project-URL: Homepage, https://github.com/KennethJAllen/proper-pixel-art
Project-URL: Repository, https://github.com/KennethJAllen/proper-pixel-art
Project-URL: Issues, https://github.com/KennethJAllen/proper-pixel-art/issues
Author: Kenneth Allen
License-Expression: MIT
License-File: LICENSE
Keywords: game-dev,generative-ai,generative-art,image-processing,pixel-art,sprites
Classifier: Development Status :: 4 - Beta
Classifier: Intended Audience :: Developers
Classifier: Programming Language :: Python :: 3.12
Classifier: Topic :: Games/Entertainment
Classifier: Topic :: Multimedia :: Graphics :: Graphics Conversion
Requires-Python: >=3.12
Requires-Dist: numpy>=2.2.4
Requires-Dist: opencv-python>=4.11.0.86
Requires-Dist: pillow>=11.1.0
Provides-Extra: scripts
Requires-Dist: openai>=1.54.0; extra == 'scripts'
Requires-Dist: python-dotenv>=1.0.0; extra == 'scripts'
Provides-Extra: web
Requires-Dist: gradio>=5.0.0; extra == 'web'
